torm_storage/Torm.py
torm_storage/__init__.py
torm_storage-1.3.1.dist-info/METADATA
torm_storage-1.3.1.dist-info/WHEEL
torm_storage-1.3.1.dist-info/RECORD
